AUTHORS.txt
LICENSE.txt
README.md
boilergen.py
setup.cfg
setup.py
text-office.py
boiler_templates/dtpt-1.md
text_office/__init__.py
text_office.egg-info/PKG-INFO
text_office.egg-info/SOURCES.txt
text_office.egg-info/dependency_links.txt
text_office.egg-info/not-zip-safe
text_office.egg-info/requires.txt
text_office.egg-info/top_level.txt
text_office/boilers/__init__.py
text_office/boilers/kvsub.py
text_office/boilers/vapt.py
text_office/md/__init__.py
text_office/md/documentx.py
text_office/md/format_tag.py
text_office/utils/__init__.py
text_office/utils/docx_helper.py
text_office/utils/errx_helper.py
text_office/utils/log_helper.py
text_office/utils/parsers.py
text_office/utils/path_helper.py
text_office/utils/vapt_helper.py