Metadata-Version: 2.1
Name: text-office
Version: 0.2.7
Summary: a python module to create office documents from text-based files (e.g., markdown, xml)
Home-page: https://github.com/toranova/text-office/
Download-URL: https://github.com/ToraNova/text-office/archive/refs/tags/v0.2.7.tar.gz
Author: Chia Jason
Author-email: chia_jason96@live.com
License: AGPL-3.0-or-later
Keywords: docx,md,xml
Classifier: Development Status :: 3 - Alpha
Classifier: Programming Language :: Python :: 3
Classifier: License :: OSI Approved :: GNU Affero General Public License v3 or later (AGPLv3+)
Classifier: Operating System :: OS Independent
Classifier: Intended Audience :: Developers
License-File: LICENSE.txt
License-File: AUTHORS.txt
